ezkfg/__init__.py
ezkfg/config.py
ezkfg/handler/__init__.py
ezkfg/handler/base_handler.py
ezkfg/handler/ini_handler.py
ezkfg/handler/json_handler.py
ezkfg/handler/py_handler.py
ezkfg/handler/yaml_handler.py
ezkfg-0.0.6.dist-info/LICENSE
ezkfg-0.0.6.dist-info/METADATA
ezkfg-0.0.6.dist-info/WHEEL
ezkfg-0.0.6.dist-info/top_level.txt
ezkfg-0.0.6.dist-info/RECORD
