Metadata-Version: 2.1
Name: ezkfg
Version: 0.0.6
Summary: Easy Configuration
Home-page: http://github.com/beiyuouo/ezkfg
Author: Bingjie Yan
Author-email: bj.yan.pa@qq.com
License: Apache-2.0 License
Keywords: configuration,config
Requires-Python: >=3.6
License-File: LICENSE
Requires-Dist: PyYAML
